.clang-format
COPYING.LESSERv3
CPPLINT.cfg
LICENSE
MANIFEST.in
README.md
bumpver.toml
makefile
pyproject.toml
setup.py
demo/demo_kp.py
demo/demo_kp_tiny.py
demo/demo_kp_tiny_sa.py
demo/draft_pyfcore.py
optframe/__init__.py
optframe/components.py
optframe/core.py
optframe/engine.py
optframe/heuristics.py
optframe/optframe_lib.cpp
optframe/optframe_lib.h
optframe/protocols.py
optframe.egg-info/PKG-INFO
optframe.egg-info/SOURCES.txt
optframe.egg-info/dependency_links.txt
optframe.egg-info/requires.txt
optframe.egg-info/top_level.txt
tests/test_pkg_engine_kp.py