Metadata-Version: 2.1
Name: optframe
Version: 5.0.28rc0
Summary: Python bindings for OptFrame Functional Core
Author-email: Igor Machado Coelho <igormcoelho@proton.me>
License: Copyright (c) 2023 OptFrame Developers
Project-URL: Homepage, https://github.com/optframe/pyoptframe-dev
Keywords: optframe,optimization,metaheuristics
Classifier: License :: OSI Approved :: MIT License
Classifier: Programming Language :: Python
Classifier: Programming Language :: Python :: 3
Requires-Python: >=3.9
License-File: LICENSE
License-File: COPYING.LESSERv3
Provides-Extra: dev
Requires-Dist: black; extra == "dev"
Requires-Dist: bumpver; extra == "dev"
Requires-Dist: isort; extra == "dev"
Requires-Dist: pip-tools; extra == "dev"
Requires-Dist: pytest; extra == "dev"
